<include>
  <!--setting items-->
  <window name="set_form" pos="0,0,-0,-0" skin="skin_bkmain">
    <caption pos="5,5,-5,34">
      <imgbtn name="btn_close" skin="_skin.sys.btn.close"    pos="-40,0" tip="close" animate="1"/>
      <imgbtn name="btn_min" skin="_skin.sys.btn.minimize" pos="-75,0" animate="1" />
    </caption>
    <window pos="0,35,-0,-55">
      <scrolltext show="1" pos="10,20,-10,@30" rollType="1" font="size:20" colorText="@color/comblue" speed="10" >@string/softwareinfo</scrolltext>
      <tabctrl name="tab_settings" pos="0,50,-0,-0" animateSteps="10" curSel="0" tabAlign="left" tabSkin="skin_tab_left"   tabInterSize="2" tabHeight="40" tabWidth="250" icon-x="5" icon-y="4"  drawFocusRect="0" iconSkin="skin_tabicon">
       <page title="@string/style" font="size:20">
         <include src="LAYOUT:PAGE_STYLE"/>
         </page>
        <page title="@string/custom" colorBkgnd="@color/green">
          <text name="test" pos="|0,|0">this is seconde test text</text>
        </page>
       </tabctrl>
    </window>
  </window>

</include>
